CHANGELOG.rst
MANIFEST.in
README.rst
setup.py
Products/__init__.py
Products.ZSPARQLMethod.egg-info/PKG-INFO
Products.ZSPARQLMethod.egg-info/SOURCES.txt
Products.ZSPARQLMethod.egg-info/dependency_links.txt
Products.ZSPARQLMethod.egg-info/not-zip-safe
Products.ZSPARQLMethod.egg-info/requires.txt
Products.ZSPARQLMethod.egg-info/top_level.txt
Products/ZSPARQLMethod/Method.py
Products/ZSPARQLMethod/__init__.py
Products/ZSPARQLMethod/version.txt
Products/ZSPARQLMethod/tests/__init__.py
Products/ZSPARQLMethod/tests/mock_db.py
Products/ZSPARQLMethod/tests/sparql-get_lang_by_name-da.xml
Products/ZSPARQLMethod/tests/sparql-get_lang_names.xml
Products/ZSPARQLMethod/tests/sparql-get_languages.xml
Products/ZSPARQLMethod/tests/test_browser.py
Products/ZSPARQLMethod/tests/test_method.py
Products/ZSPARQLMethod/tests/zope_wsgi.py
Products/ZSPARQLMethod/www/method.gif
Products/ZSPARQLMethod/zpt/method_add.zpt
Products/ZSPARQLMethod/zpt/method_edit.zpt
Products/ZSPARQLMethod/zpt/method_test.zpt
docs/HISTORY.txt
docs/Makefile
docs/api.rst
docs/conf.py
docs/index.rst
docs/installation.rst
docs/zmi.rst
docs/zmi-screenshots/1.png
docs/zmi-screenshots/2.png
docs/zmi-screenshots/3.png
docs/zmi-screenshots/4.png
docs/zmi-screenshots/5.png
docs/zmi-screenshots/6.png